ommi/__init__.py
ommi/contextual_method.py
ommi/database/__init__.py
ommi/database/ommi.py
ommi/database/query_results.py
ommi/database/results.py
ommi/database_actions.py
ommi/database_statuses.py
ommi/driver_context.py
ommi/drivers/__init__.py
ommi/drivers/drivers.py
ommi/drivers/exceptions.py
ommi/drivers/transactions.py
ommi/ext/.DS_Store
ommi/ext/drivers/mongodb/__init__.py
ommi/ext/drivers/mongodb/add_action.py
ommi/ext/drivers/mongodb/connection_protocol.py
ommi/ext/drivers/mongodb/count_action.py
ommi/ext/drivers/mongodb/delete_action.py
ommi/ext/drivers/mongodb/driver.py
ommi/ext/drivers/mongodb/fetch_action.py
ommi/ext/drivers/mongodb/find_action.py
ommi/ext/drivers/mongodb/mongodb_add.py
ommi/ext/drivers/mongodb/mongodb_delete.py
ommi/ext/drivers/mongodb/mongodb_fetch.py
ommi/ext/drivers/mongodb/mongodb_query_builder.py
ommi/ext/drivers/mongodb/mongodb_schema.py
ommi/ext/drivers/mongodb/mongodb_update.py
ommi/ext/drivers/mongodb/mongodb_utils.py
ommi/ext/drivers/mongodb/schema_action.py
ommi/ext/drivers/mongodb/set_fields_action.py
ommi/ext/drivers/mongodb/transaction.py
ommi/ext/drivers/mongodb/utils.py
ommi/ext/drivers/postgresql/__init__.py
ommi/ext/drivers/postgresql/add_action.py
ommi/ext/drivers/postgresql/add_query.py
ommi/ext/drivers/postgresql/connection_protocol.py
ommi/ext/drivers/postgresql/count_action.py
ommi/ext/drivers/postgresql/count_query.py
ommi/ext/drivers/postgresql/delete_action.py
ommi/ext/drivers/postgresql/delete_query.py
ommi/ext/drivers/postgresql/driver.py
ommi/ext/drivers/postgresql/fetch_action.py
ommi/ext/drivers/postgresql/fetch_query.py
ommi/ext/drivers/postgresql/find_action.py
ommi/ext/drivers/postgresql/schema_action.py
ommi/ext/drivers/postgresql/schema_management.py
ommi/ext/drivers/postgresql/set_fields_action.py
ommi/ext/drivers/postgresql/shared_types.py
ommi/ext/drivers/postgresql/transaction.py
ommi/ext/drivers/postgresql/transactions.py
ommi/ext/drivers/postgresql/update_query.py
ommi-0.2.0.dist-info/LICENSE
ommi-0.2.0.dist-info/METADATA
ommi-0.2.0.dist-info/WHEEL
ommi-0.2.0.dist-info/RECORD
