Metadata-Version: 2.3
Name: ommi
Version: 0.2.0
Summary: A portable object model mapper that can work with any database and model library (dataclasses, Attrs, Pydantic, etc.). It is designed for the general case to support the largest possible number of databases.
License: MIT
Keywords: database,orm,object model mapper,dataclasses,attrs,pydantic,sqlite
Author: Zech Zimmerman
Author-email: hi@zech.codes
Requires-Python: >=3.12,<4.0
Classifier: License :: OSI Approved :: MIT License
Classifier: Programming Language :: Python :: 3
Classifier: Programming Language :: Python :: 3.12
Classifier: Programming Language :: Python :: 3.13
Requires-Dist: tramp (>=0.1.17,<0.2.0)
Project-URL: Homepage, https://github.com/ZechCodes/Ommi
